docs/Makefile
docs/api.rst
docs/architecture_rst_to_do
docs/asphere.html
docs/conf.py
docs/documenteer.toml
docs/index.rst
docs/installation.rst
docs/introduction.rst
docs/mollweide.html
docs/planisphere.html
docs/tutorials.rst
docs/usage.rst
docs/usage_figures/adjusted_healpix.html
docs/usage_figures/adjusted_planisphere.png
docs/usage_figures/basic_healpix.html
docs/usage_figures/basic_planisphere.html
docs/usage_figures/simple_horizon.html
notebooks/exposures.txt
notebooks/intro_example.ipynb
notebooks/r_depth.fits
notebooks/rubin_idealized.txt
notebooks/sample_survey_footprint.fits
notebooks/uranography.ipynb
tests/__init__.py
tests/helpers.py
tests/test_armillary.py
tests/test_horizon.py
tests/test_mollweide.py
tests/test_planisphere.py
tests/test_readjs.py
tests/test_sphere.py
tests/test_spheremap.py
tests/test_stars.py
uranography/__init__.py
uranography/api.py
uranography/armillary.py
uranography/camera.py
uranography/horizon.py
uranography/mollweide.py
uranography/planisphere.py
uranography/readjs.py
uranography/sphere.py
uranography/spheremap.py
uranography/stars.py
uranography/version.py
uranography/js/coord_utils.js
uranography/js/horizon.js
uranography/js/hp.js
uranography/js/laea.js
uranography/js/match_eq_horizon_sliders.js
uranography/js/mollweide.js
uranography/js/orthographic.js
uranography/js/update.js
uranography/js/update_map.js
uranography-1.4.1.dist-info/licenses/LICENSE
uranography-1.4.1.dist-info/METADATA
uranography-1.4.1.dist-info/WHEEL
uranography-1.4.1.dist-info/top_level.txt
uranography-1.4.1.dist-info/RECORD
