Metadata-Version: 2.4
Name: uranography
Version: 1.4.1
Summary: Tools for visualization of the celestial sphere.
Author-email: "Eric H. Neilsen, Jr." <neilsen@fnal.gov>
Project-URL: Homepage, https://github.com/lsst/uranography
Classifier: Intended Audience :: Science/Research
Classifier: Operating System :: OS Independent
Classifier: Programming Language :: Python :: 3
Classifier: Programming Language :: Python :: 3.11
Classifier: Programming Language :: Python :: 3.12
Classifier: Programming Language :: Python :: 3.13
Classifier: Topic :: Scientific/Engineering :: Astronomy
License-File: LICENSE
Requires-Dist: numpy
Requires-Dist: pandas
Requires-Dist: astropy>=5.3
Requires-Dist: healpy
Requires-Dist: healsparse
Requires-Dist: bokeh>=3.1.1
Requires-Dist: panel>=1.1.0
Requires-Dist: colorcet
Requires-Dist: jupyter
Requires-Dist: nbconvert
Requires-Dist: selenium>=4.10.0
Provides-Extra: test
Requires-Dist: pytest; extra == "test"
Dynamic: license-file
